pyleap/__init__.py
pyleap/audio.py
pyleap/collision.py
pyleap/color.py
pyleap/constant_colors.py
pyleap/key.py
pyleap/mouse.py
pyleap/resource.py
pyleap/transform.py
pyleap/util.py
pyleap/window.py
pyleap/shape/__init__.py
pyleap/shape/circle.py
pyleap/shape/ellipse.py
pyleap/shape/line.py
pyleap/shape/point.py
pyleap/shape/polygon.py
pyleap/shape/rectangle.py
pyleap/shape/shape.py
pyleap/shape/sprite.py
pyleap/shape/text.py
pyleap-2022.4.5.dist-info/LICENSE
pyleap-2022.4.5.dist-info/METADATA
pyleap-2022.4.5.dist-info/WHEEL
pyleap-2022.4.5.dist-info/top_level.txt
pyleap-2022.4.5.dist-info/RECORD
