Metadata-Version: 2.1
Name: pyleap
Version: 2022.4.5
Summary: A simple 2D game engine base on pyglet
Home-page: http://github.com/XRDX/pyleap
Author: Vic Wang
Author-email: 305880887@qq.com
License: UNKNOWN
Platform: UNKNOWN
Classifier: Programming Language :: Python :: 3
Classifier: License :: OSI Approved :: BSD License
Classifier: Operating System :: OS Independent
License-File: LICENSE
Requires-Dist: pyglet (==1.5.11)
Requires-Dist: leaptask (>=2020.12.14)
